{
  "command_eng": "Change the air purifier in the bedroom to sleep mode.",
  "connected_devices": {
    "Bedroom_AirPurifier": {
      "category": [
        "AirPurifier"
      ],
      "tags": [
        "Bedroom",
        "AirPurifier"
      ]
    },
    "LivingRoom_AirPurifier": {
      "category": [
        "AirPurifier"
      ],
      "tags": [
        "LivingRoom",
        "AirPurifier"
      ]
    }
  },
  "ir": {
    "timeline": [
      {
        "op": "start_at",
        "anchor": "now"
      },
      {
        "op": "call",
        "target": "AirPurifier.SetAirPurifierMode",
        "args": {
          "Mode": "sleep"
        }
      }
    ]
  },
  "joi_block": {
    "name": "Scenario",
    "cron": "",
    "period": 0,
    "script": "(#Bedroom #AirPurifier).airPurifier_setAirPurifierMode(\"sleep\")"
  },
  "code": "{\n  \"name\": \"Scenario\",\n  \"cron\": \"\",\n  \"period\": 0,\n  \"script\": \"(#Bedroom #AirPurifier).airPurifier_setAirPurifierMode(\\\"sleep\\\")\"\n}"
}