{
  "command_eng": "Each time button 4 of the multi-button is pressed, cycle the living room light brightness through 25→50→75→100→25.",
  "connected_devices": {
    "LR_MB": {
      "category": [
        "MultiButton"
      ],
      "tags": [
        "LivingRoom",
        "MultiButton"
      ]
    },
    "Bedroom_MB": {
      "category": [
        "MultiButton"
      ],
      "tags": [
        "Bedroom",
        "MultiButton"
      ]
    },
    "LR_Light_1": {
      "category": [
        "Light"
      ],
      "tags": [
        "LivingRoom",
        "Light"
      ]
    },
    "LR_Light_2": {
      "category": [
        "Light"
      ],
      "tags": [
        "LivingRoom",
        "Light"
      ]
    },
    "Bedroom_Light": {
      "category": [
        "Light"
      ],
      "tags": [
        "Bedroom",
        "Light"
      ]
    }
  },
  "ir": {
    "timeline": [
      {
        "op": "start_at",
        "anchor": "now"
      },
      {
        "op": "cycle",
        "until": null,
        "period": "100 MSEC",
        "body": [
          {
            "op": "wait",
            "cond": "MultiButton.Button4 == true",
            "edge": "rising"
          },
          {
            "op": "call",
            "target": "Light.MoveToBrightness",
            "args": {
              "Brightness": 25.0,
              "Rate": 0.0
            }
          },
          {
            "op": "call",
            "target": "Light.MoveToBrightness",
            "args": {
              "Brightness": 50.0,
              "Rate": 0.0
            }
          },
          {
            "op": "call",
            "target": "Light.MoveToBrightness",
            "args": {
              "Brightness": 75.0,
              "Rate": 0.0
            }
          },
          {
            "op": "call",
            "target": "Light.MoveToBrightness",
            "args": {
              "Brightness": 100.0,
              "Rate": 0.0
            }
          },
          {
            "op": "call",
            "target": "Light.MoveToBrightness",
            "args": {
              "Brightness": 25.0,
              "Rate": 0.0
            }
          }
        ]
      }
    ]
  },
  "joi_block": {
    "name": "Scenario",
    "cron": "",
    "period": 100,
    "script": "triggered := false\nif ((#MultiButton #LivingRoom).multiButton_button4 == true) {\nif (triggered == false) {\n(#Light #LivingRoom).light_moveToBrightness(25.0, 0.0)\n(#Light #LivingRoom).light_moveToBrightness(50.0, 0.0)\n(#Light #LivingRoom).light_moveToBrightness(75.0, 0.0)\n(#Light #LivingRoom).light_moveToBrightness(100.0, 0.0)\n(#Light #LivingRoom).light_moveToBrightness(25.0, 0.0)\n        triggered = true\n}\n}\nelse {\ntriggered = false\n}"
  },
  "code": "{\n  \"name\": \"Scenario\",\n  \"cron\": \"\",\n  \"period\": 100,\n  \"script\": \"triggered := false\nif ((#MultiButton #LivingRoom).multiButton_button4 == true) {\nif (triggered == false) {\n(#Light #LivingRoom).light_moveToBrightness(25.0, 0.0)\n(#Light #LivingRoom).light_moveToBrightness(50.0, 0.0)\n(#Light #LivingRoom).light_moveToBrightness(75.0, 0.0)\n(#Light #LivingRoom).light_moveToBrightness(100.0, 0.0)\n(#Light #LivingRoom).light_moveToBrightness(25.0, 0.0)\n        triggered = true\n}\n}\nelse {\ntriggered = false\n}\"\n}"
}